HappyRandomBirthday/HappyRandomBirthday.py
HappyRandomBirthday/__init__.py
HappyRandomBirthday-0.4.dist-info/LICENSE
HappyRandomBirthday-0.4.dist-info/METADATA
HappyRandomBirthday-0.4.dist-info/WHEEL
HappyRandomBirthday-0.4.dist-info/top_level.txt
HappyRandomBirthday-0.4.dist-info/RECORD
