Metadata-Version: 2.1
Name: HappyRandomBirthday
Version: 0.4
Summary: Virtual Random Birthday cards
Author: Pola y Raza
License: UNKNOWN
Platform: UNKNOWN
License-File: LICENSE
